backup_devops/__init__.py
backup_devops/__main__.py
backup_devops/app_backup.py
backup_devops/git_operations.py
backup_devops/helpers.py
backup_devops-0.4.0.dist-info/LICENSE
backup_devops-0.4.0.dist-info/METADATA
backup_devops-0.4.0.dist-info/WHEEL
backup_devops-0.4.0.dist-info/RECORD
