Metadata-Version: 2.1
Name: backup-devops
Version: 0.4.0
Summary: 
License: MIT
Author: eric-therond
Author-email: eric.therond.fr@gmail.com
Requires-Python: >=3.10
Classifier: License :: OSI Approved :: MIT License
Classifier: Programming Language :: Python :: 3
Classifier: Programming Language :: Python :: 3.10
Classifier: Programming Language :: Python :: 3.11
Classifier: Programming Language :: Python :: 3.12
Requires-Dist: azure-devops (>=7.1.0b4,<8.0.0)
Requires-Dist: gitpython (>=3.1.41,<4.0.0)
